[
  {
    "sentence_id": "HCH_010_097_000001",
    "sentence": "耶律斡特剌，字乙辛隱，許國王寅底石六世孫。",
    "entities": [
      {
        "text": "耶律斡特剌",
        "label": "PER"
      },
      {
        "text": "乙辛隱",
        "label": "PER"
      },
      {
        "text": "許國王",
        "label": "TITLE"
      },
      {
        "text": "寅底石",
        "label": "ORG"
      },
      {
        "text": "六世",
        "label": "NUM"
      }
    ]
  },
  {
    "sentence_id": "HCH_010_097_000002",
    "sentence": "少不喜官祿，年四十一，始補本班郎君。",
    "entities": [
      {
        "text": "四十一",
        "label": "NUM"
      }
    ]
  },
  {
    "sentence_id": "HCH_010_097_000003",
    "sentence": "時樞密使耶律乙辛擅權，讒害忠良，斡特剌恐禍及，深自抑畏。",
    "entities": [
      {
        "text": "樞密使",
        "label": "TITLE"
      },
      {
        "text": "耶律乙辛",
        "label": "PER"
      }
    ]
  },
  {
    "sentence_id": "HCH_010_097_000004",
    "sentence": "大康中，為宿直官，歷左、右護衛太保。",
    "entities": [
      {
        "text": "宿直官",
        "label": "TITLE"
      },
      {
        "text": "護衛太保",
        "label": "TITLE"
      }
    ]
  },
  {
    "sentence_id": "HCH_010_097_000005",
    "sentence": "大安元年，升燕王傅，徙左夷離畢。",
    "entities": [
      {
        "text": "大安元年",
        "label": "TME"
      },
      {
        "text": "燕王",
        "label": "TITLE"
      },
      {
        "text": "左夷離畢",
        "label": "TITLE"
      }
    ]
  },
  {
    "sentence_id": "HCH_010_097_000006",
    "sentence": "四年，改北院樞密副使。",
    "entities": [
      {
        "text": "四年",
        "label": "TME"
      },
      {
        "text": "北院樞密副使",
        "label": "TITLE"
      }
    ]
  },
  {
    "sentence_id": "HCH_010_097_000007",
    "sentence": "帝賜詩褒之，遷知北院樞密使事，賜翼聖佐義功臣。",
    "entities": [
      {
        "text": "北院樞密使",
        "label": "TITLE"
      },
      {
        "text": "翼聖佐義功臣",
        "label": "ORG"
      }
    ]
  },
  {
    "sentence_id": "HCH_010_097_000008",
    "sentence": "北阻卜酋長磨古斯叛，斡特剌率兵進討。",
    "entities": [
      {
        "text": "北阻卜",
        "label": "ORG"
      },
      {
        "text": "磨古斯",
        "label": "PER"
      },
      {
        "text": "斡特剌",
        "label": "PER"
      }
    ]
  },
  {
    "sentence_id": "HCH_010_097_000009",
    "sentence": "會天大雪，敗磨古斯四別部，斬首千餘級，拜西北路招討使，封漆水郡王，加賜宣力守正功臣。",
    "entities": [
      {
        "text": "磨古斯",
        "label": "PER"
      },
      {
        "text": "四別部",
        "label": "ORG"
      },
      {
        "text": "千餘",
        "label": "NUM"
      },
      {
        "text": "招討使",
        "label": "TITLE"
      },
      {
        "text": "漆水郡王",
        "label": "TITLE"
      },
      {
        "text": "宣力守正功臣",
        "label": "TITLE"
      }
    ]
  },
  {
    "sentence_id": "HCH_010_097_000010",
    "sentence": "尋拜南府宰相。",
    "entities": [
      {
        "text": "南府宰相",
        "label": "TITLE"
      }
    ]
  },
  {
    "sentence_id": "HCH_010_097_000011",
    "sentence": "復討閘古胡裏扒部，破之，召為契丹行宮都部署。",
    "entities": [
      {
        "text": "閘古胡裏扒部",
        "label": "ORG"
      },
      {
        "text": "契丹行宮都部署",
        "label": "TITLE"
      }
    ]
  },
  {
    "sentence_id": "HCH_010_097_000012",
    "sentence": "先是，北、南府有訟，各州府得就按之；比歲，非奉樞密檄，不得鞫問，以故訟者稽留。",
    "entities": []
  },
  {
    "sentence_id": "HCH_010_097_000013",
    "sentence": "斡特剌奏請如舊，從之。",
    "entities": [
      {
        "text": "斡特剌",
        "label": "PER"
      }
    ]
  },
  {
    "sentence_id": "HCH_010_097_000014",
    "sentence": "壽隆五年，復為西北路招討使，討耶睹刮部，俘斬甚眾，獲馬、駝、牛、羊各數萬。",
    "entities": [
      {
        "text": "壽隆五年",
        "label": "TME"
      },
      {
        "text": "西北路招討使",
        "label": "TITLE"
      },
      {
        "text": "耶睹刮部",
        "label": "ORG"
      }
    ]
  },
  {
    "sentence_id": "HCH_010_097_000015",
    "sentence": "明年，擒磨古斯，加守太保，賜奉國匡化功臣。",
    "entities": [
      {
        "text": "明年",
        "label": "TME"
      },
      {
        "text": "磨古斯",
        "label": "PER"
      },
      {
        "text": "太保",
        "label": "TITLE"
      },
      {
        "text": "奉國匡化功臣",
        "label": "TITLE"
      }
    ]
  },
  {
    "sentence_id": "HCH_010_097_000016",
    "sentence": "乾統初，乞致仕，不許，止罷招討。",
    "entities": []
  },
  {
    "sentence_id": "HCH_010_097_000017",
    "sentence": "復兼南院樞密使，封混同郡王。",
    "entities": [
      {
        "text": "南院樞密使",
        "label": "TITLE"
      },
      {
        "text": "混同郡王",
        "label": "TITLE"
      }
    ]
  },
  {
    "sentence_id": "HCH_010_097_000018",
    "sentence": "遷北院樞密使，加守太師，賜推誠贊治功臣。",
    "entities": [
      {
        "text": "北院樞密使",
        "label": "TITLE"
      },
      {
        "text": "太師",
        "label": "TITLE"
      },
      {
        "text": "推誠贊治功臣",
        "label": "TITLE"
      }
    ]
  },
  {
    "sentence_id": "HCH_010_097_000019",
    "sentence": "致仕，薨，謚曰敬肅。",
    "entities": [
      {
        "text": "致仕",
        "label": "TITLE"
      },
      {
        "text": "敬肅",
        "label": "TITLE"
      }
    ]
  },
  {
    "sentence_id": "HCH_010_097_000020",
    "sentence": "孩裏，字胡輦，回鶻人。",
    "entities": [
      {
        "text": "孩裏",
        "label": "PER"
      },
      {
        "text": "胡輦",
        "label": "PER"
      },
      {
        "text": "回鶻",
        "label": "ORG"
      }
    ]
  },
  {
    "sentence_id": "HCH_010_097_000021",
    "sentence": "其先在太祖時來貢，願留，因任用之。",
    "entities": [
      {
        "text": "太祖",
        "label": "TITLE"
      }
    ]
  },
  {
    "sentence_id": "HCH_010_097_000022",
    "sentence": "孩裏重熙間歷近侍長。",
    "entities": [
      {
        "text": "孩裏",
        "label": "PER"
      }
    ]
  },
  {
    "sentence_id": "HCH_010_097_000023",
    "sentence": "清寧九年，討重元之亂有功，加金吾衛上將軍，賜平亂功臣。",
    "entities": [
      {
        "text": "清寧九年",
        "label": "TME"
      },
      {
        "text": "重元",
        "label": "PER"
      },
      {
        "text": "金吾衛上將軍",
        "label": "TITLE"
      },
      {
        "text": "平亂功臣",
        "label": "TITLE"
      }
    ]
  },
  {
    "sentence_id": "HCH_010_097_000024",
    "sentence": "累遷殿前都點檢，以宿衛嚴肅稱。",
    "entities": [
      {
        "text": "殿前都點檢",
        "label": "TITLE"
      }
    ]
  },
  {
    "sentence_id": "HCH_010_097_000025",
    "sentence": "大康初，加守太子太保。",
    "entities": [
      {
        "text": "太子太保",
        "label": "TITLE"
      }
    ]
  },
  {
    "sentence_id": "HCH_010_097_000026",
    "sentence": "二年，加同中書門下平章事。",
    "entities": [
      {
        "text": "二年",
        "label": "TME"
      },
      {
        "text": "同中書門下平章事",
        "label": "TITLE"
      }
    ]
  },
  {
    "sentence_id": "HCH_010_097_000027",
    "sentence": "三年，改同知南院宣徽使事。",
    "entities": [
      {
        "text": "三年",
        "label": "TME"
      },
      {
        "text": "同知南院宣徽使事",
        "label": "TITLE"
      }
    ]
  },
  {
    "sentence_id": "HCH_010_097_000028",
    "sentence": "會耶律乙辛出守中京，孩裏入賀；及議復召，陳其不可。",
    "entities": [
      {
        "text": "耶律乙辛",
        "label": "PER"
      },
      {
        "text": "中京",
        "label": "LOC"
      },
      {
        "text": "孩裏",
        "label": "PER"
      }
    ]
  },
  {
    "sentence_id": "HCH_010_097_000029",
    "sentence": "後乙辛再入樞府，出孩裏為廣利軍節度使。",
    "entities": [
      {
        "text": "乙辛",
        "label": "PER"
      },
      {
        "text": "樞府",
        "label": "LOC"
      },
      {
        "text": "孩裏",
        "label": "PER"
      },
      {
        "text": "廣利軍",
        "label": "LOC"
      },
      {
        "text": "節度使",
        "label": "TITLE"
      }
    ]
  },
  {
    "sentence_id": "HCH_010_097_000030",
    "sentence": "及皇太子被誣，孩裏當連坐，有詔勿問。",
    "entities": [
      {
        "text": "皇太子",
        "label": "TITLE"
      },
      {
        "text": "孩裏",
        "label": "PER"
      }
    ]
  },
  {
    "sentence_id": "HCH_010_097_000031",
    "sentence": "大安初，歷品達魯虢部節度使。",
    "entities": [
      {
        "text": "達魯虢部",
        "label": "ORG"
      },
      {
        "text": "節度使",
        "label": "TITLE"
      }
    ]
  },
  {
    "sentence_id": "HCH_010_097_000032",
    "sentence": "壽隆五年，有疾，自言吾數已盡，卻醫藥，卒，年七十七。",
    "entities": [
      {
        "text": "壽隆五年",
        "label": "TME"
      },
      {
        "text": "七十七",
        "label": "NUM"
      }
    ]
  },
  {
    "sentence_id": "HCH_010_097_000033",
    "sentence": "孩裏素信浮圖。",
    "entities": [
      {
        "text": "孩裏素",
        "label": "PER"
      },
      {
        "text": "浮圖",
        "label": "ORG"
      }
    ]
  },
  {
    "sentence_id": "HCH_010_097_000034",
    "sentence": "清寧初，從上獵，墮馬，憒而復蘇。",
    "entities": []
  },
  {
    "sentence_id": "HCH_010_097_000035",
    "sentence": "言始見二人引至一城，宮室宏敞，有衣絳袍人坐殿上，左右列侍，導孩裏升階。",
    "entities": [
      {
        "text": "二人",
        "label": "NUM"
      },
      {
        "text": "一城",
        "label": "NUM"
      },
      {
        "text": "孩裏",
        "label": "PER"
      }
    ]
  },
  {
    "sentence_id": "HCH_010_097_000036",
    "sentence": "持牘者示之曰：「本取大腹骨欲，誤執汝。」",
    "entities": []
  },
  {
    "sentence_id": "HCH_010_097_000037",
    "sentence": "牘上書「官至使相，壽七十七」。",
    "entities": [
      {
        "text": "使相",
        "label": "TITLE"
      },
      {
        "text": "七十七",
        "label": "NUM"
      }
    ]
  },
  {
    "sentence_id": "HCH_010_097_000038",
    "sentence": "須臾還，擠之大壑而寤。",
    "entities": []
  },
  {
    "sentence_id": "HCH_010_097_000039",
    "sentence": "道宗聞之，命書其事。",
    "entities": [
      {
        "text": "道宗",
        "label": "TITLE"
      }
    ]
  },
  {
    "sentence_id": "HCH_010_097_000040",
    "sentence": "後皆驗。",
    "entities": []
  },
  {
    "sentence_id": "HCH_010_097_000041",
    "sentence": "竇景庸，中京人，中書令振之子。",
    "entities": [
      {
        "text": "竇景庸",
        "label": "PER"
      },
      {
        "text": "中京",
        "label": "LOC"
      },
      {
        "text": "中書令",
        "label": "TITLE"
      }
    ]
  },
  {
    "sentence_id": "HCH_010_097_000042",
    "sentence": "聰敏好學。",
    "entities": []
  },
  {
    "sentence_id": "HCH_010_097_000043",
    "sentence": "清寧中，第進士，授秘書省校書郎，累遷少府少監。",
    "entities": []
  },
  {
    "sentence_id": "HCH_010_097_000044",
    "sentence": "咸雍六年，授樞密直學士，尋知漢人行宮副部署事。",
    "entities": [
      {
        "text": "咸雍六年",
        "label": "TME"
      },
      {
        "text": "樞密直學士",
        "label": "TITLE"
      },
      {
        "text": "漢人行宮",
        "label": "LOC"
      },
      {
        "text": "副部署",
        "label": "TITLE"
      }
    ]
  },
  {
    "sentence_id": "HCH_010_097_000045",
    "sentence": "大安初，遷南院樞密副使，監修國史，知樞密院事，賜同德功臣，封陳國公。",
    "entities": [
      {
        "text": "南院樞密副使",
        "label": "TITLE"
      },
      {
        "text": "監修國史",
        "label": "TITLE"
      },
      {
        "text": "知樞密院事",
        "label": "TITLE"
      },
      {
        "text": "同德功臣",
        "label": "TITLE"
      },
      {
        "text": "陳國公",
        "label": "TITLE"
      }
    ]
  },
  {
    "sentence_id": "HCH_010_097_000046",
    "sentence": "有疾，表請致仕，不從，加太子太保，授武定軍節度使。",
    "entities": [
      {
        "text": "太子太保",
        "label": "TITLE"
      },
      {
        "text": "武定軍節度使",
        "label": "TITLE"
      }
    ]
  },
  {
    "sentence_id": "HCH_010_097_000047",
    "sentence": "審決冤滯，輕重得宜，以獄空聞。",
    "entities": []
  },
  {
    "sentence_id": "HCH_010_097_000048",
    "sentence": "七年，拜中京留守。",
    "entities": [
      {
        "text": "七年",
        "label": "TME"
      },
      {
        "text": "中京",
        "label": "LOC"
      },
      {
        "text": "留守",
        "label": "TITLE"
      }
    ]
  },
  {
    "sentence_id": "HCH_010_097_000049",
    "sentence": "九年薨，謚曰肅憲。",
    "entities": [
      {
        "text": "九年",
        "label": "TME"
      },
      {
        "text": "肅憲",
        "label": "TITLE"
      }
    ]
  },
  {
    "sentence_id": "HCH_010_097_000050",
    "sentence": "子瑜，三司副使。",
    "entities": [
      {
        "text": "瑜",
        "label": "PER"
      },
      {
        "text": "三司副使",
        "label": "TITLE"
      }
    ]
  },
  {
    "sentence_id": "HCH_010_097_000051",
    "sentence": "耶律引吉，字阿括，品部人。",
    "entities": [
      {
        "text": "耶律引吉",
        "label": "PER"
      },
      {
        "text": "阿括",
        "label": "PER"
      },
      {
        "text": "品部",
        "label": "ORG"
      }
    ]
  },
  {
    "sentence_id": "HCH_010_097_000052",
    "sentence": "父雙古，鎮西邊二十餘年，治尚嚴肅，不殖貨利，時多稱之。",
    "entities": [
      {
        "text": "雙古",
        "label": "PER"
      },
      {
        "text": "鎮西",
        "label": "LOC"
      }
    ]
  },
  {
    "sentence_id": "HCH_010_097_000053",
    "sentence": "引吉寅畏好義。",
    "entities": [
      {
        "text": "引吉",
        "label": "PER"
      },
      {
        "text": "寅畏",
        "label": "PER"
      }
    ]
  },
  {
    "sentence_id": "HCH_010_097_000054",
    "sentence": "以蔭補官，累遷東京副留守、北樞密院侍御。",
    "entities": [
      {
        "text": "東京",
        "label": "LOC"
      },
      {
        "text": "留守",
        "label": "TITLE"
      },
      {
        "text": "北樞密院",
        "label": "ORG"
      },
      {
        "text": "侍御",
        "label": "TITLE"
      }
    ]
  },
  {
    "sentence_id": "HCH_010_097_000055",
    "sentence": "時蕭革、蕭圖古辭等以佞見任，鬻爵納賄，引吉以直道處其間，無所阿唯。",
    "entities": [
      {
        "text": "蕭革",
        "label": "PER"
      },
      {
        "text": "蕭圖古辭",
        "label": "PER"
      },
      {
        "text": "引吉",
        "label": "PER"
      }
    ]
  },
  {
    "sentence_id": "HCH_010_097_000056",
    "sentence": "改客省使。",
    "entities": [
      {
        "text": "客省使",
        "label": "TITLE"
      }
    ]
  },
  {
    "sentence_id": "HCH_010_097_000057",
    "sentence": "時朝廷遣使括三京隱戶不得，以引吉代之，得數千餘戶。",
    "entities": [
      {
        "text": "三京",
        "label": "NUM"
      },
      {
        "text": "引吉",
        "label": "PER"
      },
      {
        "text": "數千餘戶",
        "label": "NUM"
      }
    ]
  },
  {
    "sentence_id": "HCH_010_097_000058",
    "sentence": "時昭懷太子知北南院事，選引吉為輔導。",
    "entities": [
      {
        "text": "昭懷太子",
        "label": "TITLE"
      },
      {
        "text": "引吉",
        "label": "PER"
      }
    ]
  },
  {
    "sentence_id": "HCH_010_097_000059",
    "sentence": "樞密使乙辛將傾太子，惡引吉在側，奏出之，為群牧林牙。",
    "entities": [
      {
        "text": "樞密使",
        "label": "TITLE"
      },
      {
        "text": "乙辛",
        "label": "PER"
      },
      {
        "text": "太子",
        "label": "TITLE"
      },
      {
        "text": "引吉",
        "label": "PER"
      },
      {
        "text": "群牧",
        "label": "PER"
      },
      {
        "text": "林牙",
        "label": "TITLE"
      }
    ]
  },
  {
    "sentence_id": "HCH_010_097_000060",
    "sentence": "大康元年，乙辛請賜牧地，引吉奏曰：「今牧地褊狹，畜不蕃息，豈可分賜臣下。」",
    "entities": [
      {
        "text": "大康元年",
        "label": "TME"
      },
      {
        "text": "乙辛",
        "label": "PER"
      },
      {
        "text": "引吉",
        "label": "PER"
      }
    ]
  },
  {
    "sentence_id": "HCH_010_097_000061",
    "sentence": "帝乃止。",
    "entities": []
  },
  {
    "sentence_id": "HCH_010_097_000062",
    "sentence": "乙辛由是益嫉之，除懷德軍節度使，徙漠北猾水馬群太保，卒。",
    "entities": [
      {
        "text": "乙辛",
        "label": "PER"
      },
      {
        "text": "懷德軍節度使",
        "label": "TITLE"
      },
      {
        "text": "漠北猾水馬群太保",
        "label": "TITLE"
      }
    ]
  },
  {
    "sentence_id": "HCH_010_097_000063",
    "sentence": "楊績，良鄉人。",
    "entities": [
      {
        "text": "楊績",
        "label": "PER"
      },
      {
        "text": "良鄉",
        "label": "LOC"
      }
    ]
  },
  {
    "sentence_id": "HCH_010_097_000064",
    "sentence": "太平十一年進士及第，累遷南院樞密副使。",
    "entities": [
      {
        "text": "太平十一年",
        "label": "TME"
      },
      {
        "text": "進士",
        "label": "TITLE"
      },
      {
        "text": "南院樞密副使",
        "label": "TITLE"
      }
    ]
  },
  {
    "sentence_id": "HCH_010_097_000065",
    "sentence": "與杜防、韓知白等擅給進士堂帖，降長寧軍節度使，徙知涿州。",
    "entities": [
      {
        "text": "杜防",
        "label": "PER"
      },
      {
        "text": "韓知白",
        "label": "PER"
      },
      {
        "text": "長寧軍",
        "label": "LOC"
      },
      {
        "text": "節度使",
        "label": "TITLE"
      },
      {
        "text": "涿州",
        "label": "LOC"
      }
    ]
  },
  {
    "sentence_id": "HCH_010_097_000066",
    "sentence": "清寧初，拜參知政事，兼同知樞密院事，為南府宰相。",
    "entities": [
      {
        "text": "參知政事",
        "label": "TITLE"
      },
      {
        "text": "同知樞密院事",
        "label": "TITLE"
      },
      {
        "text": "南府宰相",
        "label": "TITLE"
      }
    ]
  },
  {
    "sentence_id": "HCH_010_097_000067",
    "sentence": "九年，聞重元亂，與姚景行勤王，上嘉之。",
    "entities": [
      {
        "text": "九年",
        "label": "TME"
      },
      {
        "text": "重元",
        "label": "PER"
      },
      {
        "text": "姚景行",
        "label": "PER"
      }
    ]
  },
  {
    "sentence_id": "HCH_010_097_000068",
    "sentence": "十年，知興中府。",
    "entities": [
      {
        "text": "十年",
        "label": "TME"
      },
      {
        "text": "興中府",
        "label": "LOC"
      }
    ]
  },
  {
    "sentence_id": "HCH_010_097_000069",
    "sentence": "咸雍初，入知樞密院事。",
    "entities": [
      {
        "text": "樞密院",
        "label": "ORG"
      }
    ]
  },
  {
    "sentence_id": "HCH_010_097_000070",
    "sentence": "二年，乞致仕，不許，拜南院樞密使。",
    "entities": [
      {
        "text": "二年",
        "label": "TME"
      },
      {
        "text": "南院樞密使",
        "label": "TITLE"
      }
    ]
  },
  {
    "sentence_id": "HCH_010_097_000071",
    "sentence": "帝以績舊臣，特詔燕見，論古今治亂，人臣邪正。",
    "entities": []
  },
  {
    "sentence_id": "HCH_010_097_000072",
    "sentence": "帝曰：「方今群臣忠直，耶律玦、劉伸而已；然伸不及玦之剛介。」",
    "entities": [
      {
        "text": "耶律玦",
        "label": "PER"
      },
      {
        "text": "劉伸",
        "label": "PER"
      }
    ]
  },
  {
    "sentence_id": "HCH_010_097_000073",
    "sentence": "績拜賀曰：「何代無賢，世亂則獨善其身，主聖則兼濟天下。陛下銖分邪正，升黜分明，天下幸甚。」",
    "entities": []
  },
  {
    "sentence_id": "HCH_010_097_000074",
    "sentence": "累表告歸，不許，封趙王。",
    "entities": [
      {
        "text": "趙王",
        "label": "TITLE"
      }
    ]
  },
  {
    "sentence_id": "HCH_010_097_000075",
    "sentence": "大康中，以例改王遼西。",
    "entities": [
      {
        "text": "王遼西",
        "label": "TITLE"
      }
    ]
  },
  {
    "sentence_id": "HCH_010_097_000076",
    "sentence": "致仕，加守太保，薨。",
    "entities": [
      {
        "text": "太保",
        "label": "TITLE"
      }
    ]
  },
  {
    "sentence_id": "HCH_010_097_000077",
    "sentence": "子貴忠，知興中府。",
    "entities": [
      {
        "text": "貴忠",
        "label": "PER"
      },
      {
        "text": "興中府",
        "label": "LOC"
      }
    ]
  },
  {
    "sentence_id": "HCH_010_097_000078",
    "sentence": "趙徽，南京人。",
    "entities": [
      {
        "text": "趙徽",
        "label": "PER"
      },
      {
        "text": "南京",
        "label": "LOC"
      }
    ]
  },
  {
    "sentence_id": "HCH_010_097_000079",
    "sentence": "重熙五年，擢甲科，累遷大理正。",
    "entities": [
      {
        "text": "重熙五年",
        "label": "TME"
      },
      {
        "text": "甲科",
        "label": "TITLE"
      },
      {
        "text": "大理正",
        "label": "TITLE"
      }
    ]
  },
  {
    "sentence_id": "HCH_010_097_000080",
    "sentence": "清寧二年，銅州人妄毀三教，徽按鞫之，以狀聞，稱旨。",
    "entities": [
      {
        "text": "清寧二年",
        "label": "TME"
      },
      {
        "text": "銅州",
        "label": "LOC"
      }
    ]
  },
  {
    "sentence_id": "HCH_010_097_000081",
    "sentence": "歷煩劇，有能名。",
    "entities": []
  },
  {
    "sentence_id": "HCH_010_097_000082",
    "sentence": "累遷翰林學士承旨。",
    "entities": [
      {
        "text": "翰林學士承旨",
        "label": "TITLE"
      }
    ]
  },
  {
    "sentence_id": "HCH_010_097_000083",
    "sentence": "咸雍初，為度支使。",
    "entities": []
  },
  {
    "sentence_id": "HCH_010_097_000084",
    "sentence": "三年，拜參知政事。",
    "entities": [
      {
        "text": "三年",
        "label": "TME"
      },
      {
        "text": "參知政事",
        "label": "TITLE"
      }
    ]
  },
  {
    "sentence_id": "HCH_010_097_000085",
    "sentence": "出為武定軍節度使，及代，軍民請留。",
    "entities": [
      {
        "text": "武定軍",
        "label": "LOC"
      },
      {
        "text": "節度使",
        "label": "TITLE"
      }
    ]
  },
  {
    "sentence_id": "HCH_010_097_000086",
    "sentence": "後同知樞密院事，兼南府宰相、門下侍郎、平章事。",
    "entities": [
      {
        "text": "同知樞密院事",
        "label": "TITLE"
      },
      {
        "text": "南府宰相",
        "label": "TITLE"
      },
      {
        "text": "門下侍郎",
        "label": "TITLE"
      },
      {
        "text": "平章事",
        "label": "TITLE"
      }
    ]
  },
  {
    "sentence_id": "HCH_010_097_000087",
    "sentence": "致仕，卒。",
    "entities": []
  },
  {
    "sentence_id": "HCH_010_097_000088",
    "sentence": "追贈中書令，謚文憲。",
    "entities": [
      {
        "text": "中書令",
        "label": "TITLE"
      },
      {
        "text": "文憲",
        "label": "TITLE"
      }
    ]
  },
  {
    "sentence_id": "HCH_010_097_000089",
    "sentence": "王觀，南京人。",
    "entities": [
      {
        "text": "王觀",
        "label": "PER"
      },
      {
        "text": "南京",
        "label": "LOC"
      }
    ]
  },
  {
    "sentence_id": "HCH_010_097_000090",
    "sentence": "博學有才辯。",
    "entities": []
  },
  {
    "sentence_id": "HCH_010_097_000091",
    "sentence": "重熙七年，中進士乙科。",
    "entities": [
      {
        "text": "重熙七年",
        "label": "TME"
      },
      {
        "text": "中進士乙科",
        "label": "TITLE"
      }
    ]
  },
  {
    "sentence_id": "HCH_010_097_000092",
    "sentence": "興宗崩，充夏國報哀使；還，除給事中。",
    "entities": [
      {
        "text": "興宗",
        "label": "TITLE"
      },
      {
        "text": "夏國",
        "label": "ORG"
      },
      {
        "text": "給事中",
        "label": "TITLE"
      }
    ]
  },
  {
    "sentence_id": "HCH_010_097_000093",
    "sentence": "咸雍初，遷翰林學士。",
    "entities": [
      {
        "text": "翰林學士",
        "label": "TITLE"
      }
    ]
  },
  {
    "sentence_id": "HCH_010_097_000094",
    "sentence": "五年，兼乾文閣學士。",
    "entities": [
      {
        "text": "五年",
        "label": "TME"
      },
      {
        "text": "乾文閣學士",
        "label": "TITLE"
      }
    ]
  },
  {
    "sentence_id": "HCH_010_097_000095",
    "sentence": "七年，改南院樞密副使，賜國姓，參知政事，兼知南院樞密事。",
    "entities": [
      {
        "text": "七年",
        "label": "TME"
      },
      {
        "text": "南院樞密副使",
        "label": "TITLE"
      },
      {
        "text": "國姓",
        "label": "TITLE"
      },
      {
        "text": "參知政事",
        "label": "TITLE"
      },
      {
        "text": "南院樞密",
        "label": "TITLE"
      }
    ]
  },
  {
    "sentence_id": "HCH_010_097_000096",
    "sentence": "坐矯制修私第，削爵為民，卒。",
    "entities": []
  },
  {
    "sentence_id": "HCH_010_097_000097",
    "sentence": "耶律喜孫，字盈隱，永興宮分人。",
    "entities": [
      {
        "text": "耶律喜孫",
        "label": "PER"
      },
      {
        "text": "永興宮分",
        "label": "LOC"
      }
    ]
  },
  {
    "sentence_id": "HCH_010_097_000098",
    "sentence": "興宗在青宮，嘗居左右輔導。",
    "entities": [
      {
        "text": "興宗",
        "label": "TITLE"
      },
      {
        "text": "青宮",
        "label": "LOC"
      }
    ]
  },
  {
    "sentence_id": "HCH_010_097_000099",
    "sentence": "聖宗大漸，喜孫與馮家奴告仁德皇后同宰相蕭浞卜等謀逆事。",
    "entities": [
      {
        "text": "聖宗",
        "label": "TITLE"
      },
      {
        "text": "喜孫",
        "label": "PER"
      },
      {
        "text": "馮家奴",
        "label": "PER"
      },
      {
        "text": "仁德皇后",
        "label": "TITLE"
      },
      {
        "text": "宰相",
        "label": "TITLE"
      },
      {
        "text": "蕭浞卜",
        "label": "PER"
      }
    ]
  },
  {
    "sentence_id": "HCH_010_097_000100",
    "sentence": "及欽哀為皇太后稱制，喜孫尤見寵任。",
    "entities": [
      {
        "text": "欽哀",
        "label": "TITLE"
      },
      {
        "text": "皇太后",
        "label": "TITLE"
      },
      {
        "text": "喜孫",
        "label": "PER"
      }
    ]
  },
  {
    "sentence_id": "HCH_010_097_000101",
    "sentence": "重熙中，其子涅哥為近侍，坐事伏誅。",
    "entities": [
      {
        "text": "涅哥",
        "label": "PER"
      },
      {
        "text": "近侍",
        "label": "TITLE"
      }
    ]
  },
  {
    "sentence_id": "HCH_010_097_000102",
    "sentence": "帝以喜孫有翼戴功，且悼其子罪死，欲世其官，喜孫無所出之部，因見馬印文有品部號，使隸其部，拜南府宰相。",
    "entities": [
      {
        "text": "喜孫",
        "label": "PER"
      },
      {
        "text": "南府宰相",
        "label": "TITLE"
      }
    ]
  },
  {
    "sentence_id": "HCH_010_097_000103",
    "sentence": "尋出為東北路詳穩，卒。",
    "entities": [
      {
        "text": "東北路詳穩",
        "label": "TITLE"
      }
    ]
  },
  {
    "sentence_id": "HCH_010_097_000104",
    "sentence": "論曰：孩裏、引吉之為臣也，當乙辛擅權、蕭革貪黷之日，雖與同官，而能以正自處，不少阿唯，其過人遠矣。",
    "entities": [
      {
        "text": "孩裏",
        "label": "PER"
      },
      {
        "text": "引吉",
        "label": "PER"
      },
      {
        "text": "乙辛",
        "label": "PER"
      },
      {
        "text": "蕭革",
        "label": "PER"
      }
    ]
  },
  {
    "sentence_id": "HCH_010_097_000105",
    "sentence": "傳曰：「歲寒知松柏之後雕。」",
    "entities": []
  },
  {
    "sentence_id": "HCH_010_097_000106",
    "sentence": "二子有焉。",
    "entities": [
      {
        "text": "二子",
        "label": "NUM"
      }
    ]
  },
  {
    "sentence_id": "HCH_010_097_000107",
    "sentence": "若斡特剌之戰功，竇景庸之讞獄，楊績之忠告，亦賢矣夫。",
    "entities": [
      {
        "text": "斡特剌",
        "label": "PER"
      },
      {
        "text": "竇景庸",
        "label": "PER"
      },
      {
        "text": "楊績",
        "label": "PER"
      }
    ]
  },
  {
    "sentence_id": "HCH_010_097_000108",
    "sentence": "本元朝作品在全世界都属于公有领域，因为作者逝世已经遠遠超过100年。",
    "entities": []
  }
]