[
  {
    "sentence_id": "HCH_015_041_000001",
    "sentence": "張融字思光，吳郡吳人也。",
    "entities": [
      {
        "text": "張融",
        "label": "PER"
      },
      {
        "text": "思光",
        "label": "PER"
      },
      {
        "text": "吳郡",
        "label": "LOC"
      }
    ]
  },
  {
    "sentence_id": "HCH_015_041_000002",
    "sentence": "祖褘，晉琅邪王國郎中令。",
    "entities": [
      {
        "text": "祖褘",
        "label": "PER"
      },
      {
        "text": "晉",
        "label": "ORG"
      },
      {
        "text": "琅邪王",
        "label": "TITLE"
      },
      {
        "text": "國",
        "label": "PER"
      },
      {
        "text": "郎中令",
        "label": "TITLE"
      }
    ]
  },
  {
    "sentence_id": "HCH_015_041_000003",
    "sentence": "父暢，宋會稽太守。",
    "entities": [
      {
        "text": "暢",
        "label": "PER"
      },
      {
        "text": "宋",
        "label": "ORG"
      },
      {
        "text": "會稽",
        "label": "LOC"
      },
      {
        "text": "太守",
        "label": "TITLE"
      }
    ]
  },
  {
    "sentence_id": "HCH_015_041_000004",
    "sentence": "融年弱冠，道士同郡陸脩靜以白鷺羽麈尾扇遺融，曰：「此旣異物，以奉異人。」",
    "entities": [
      {
        "text": "陸脩靜",
        "label": "PER"
      },
      {
        "text": "白鷺羽麈尾扇",
        "label": "TITLE"
      },
      {
        "text": "異人",
        "label": "TITLE"
      }
    ]
  },
  {
    "sentence_id": "HCH_015_041_000005",
    "sentence": "宋孝武聞融有早譽，解褐爲新安王北中郎參軍。",
    "entities": [
      {
        "text": "宋",
        "label": "ORG"
      },
      {
        "text": "孝武",
        "label": "PER"
      },
      {
        "text": "新安王",
        "label": "TITLE"
      },
      {
        "text": "北中郎參軍",
        "label": "TITLE"
      }
    ]
  },
  {
    "sentence_id": "HCH_015_041_000006",
    "sentence": "孝武起新安寺，僚佐多儭錢帛，融獨儭百錢。",
    "entities": [
      {
        "text": "孝武",
        "label": "TITLE"
      },
      {
        "text": "新安寺",
        "label": "LOC"
      },
      {
        "text": "僚佐",
        "label": "ORG"
      },
      {
        "text": "融",
        "label": "PER"
      },
      {
        "text": "百錢",
        "label": "NUM"
      }
    ]
  },
  {
    "sentence_id": "HCH_015_041_000007",
    "sentence": "帝曰：「融殊貧，當序以佳祿。」",
    "entities": [
      {
        "text": "融",
        "label": "PER"
      }
    ]
  },
  {
    "sentence_id": "HCH_015_041_000008",
    "sentence": "出爲封溪令。",
    "entities": [
      {
        "text": "封溪",
        "label": "LOC"
      }
    ]
  },
  {
    "sentence_id": "HCH_015_041_000009",
    "sentence": "從叔永出後渚送之，曰：「似聞朝旨，汝尋當還。」",
    "entities": [
      {
        "text": "從叔",
        "label": "TITLE"
      },
      {
        "text": "永",
        "label": "PER"
      },
      {
        "text": "渚",
        "label": "LOC"
      }
    ]
  },
  {
    "sentence_id": "HCH_015_041_000010",
    "sentence": "融曰：「不患不還，政恐還而復去。」",
    "entities": [
      {
        "text": "融",
        "label": "PER"
      }
    ]
  },
  {
    "sentence_id": "HCH_015_041_000011",
    "sentence": "廣越嶂嶮，獠賊執融，將殺食之，融神色不動，方作洛生詠，賊異之而不害也。",
    "entities": [
      {
        "text": "獠賊",
        "label": "ORG"
      },
      {
        "text": "融",
        "label": "PER"
      }
    ]
  },
  {
    "sentence_id": "HCH_015_041_000012",
    "sentence": "浮海至交州，於海中作《海賦》曰：融文辭詭激，獨與衆異。",
    "entities": [
      {
        "text": "交州",
        "label": "LOC"
      },
      {
        "text": "海賦",
        "label": "TITLE"
      },
      {
        "text": "融",
        "label": "PER"
      }
    ]
  },
  {
    "sentence_id": "HCH_015_041_000013",
    "sentence": "後還京師，以示鎮軍將軍顧覬之，覬之曰：「卿此賦實超玄虛，但恨不道鹽耳。」",
    "entities": [
      {
        "text": "京師",
        "label": "LOC"
      },
      {
        "text": "鎮軍將軍",
        "label": "TITLE"
      },
      {
        "text": "顧覬之",
        "label": "PER"
      },
      {
        "text": "卿",
        "label": "TITLE"
      },
      {
        "text": "鹽",
        "label": "NUM"
      }
    ]
  },
  {
    "sentence_id": "HCH_015_041_000014",
    "sentence": "融卽求筆注之曰：「漉沙構白，熬波出素。積雪中春，飛霜暑路。」",
    "entities": [
      {
        "text": "融",
        "label": "PER"
      },
      {
        "text": "筆",
        "label": "NUM"
      }
    ]
  },
  {
    "sentence_id": "HCH_015_041_000015",
    "sentence": "此四句，後所足也。",
    "entities": []
  },
  {
    "sentence_id": "HCH_015_041_000016",
    "sentence": "覬之與融兄有恩好，覬之卒，融身負墳土。",
    "entities": [
      {
        "text": "覬之",
        "label": "PER"
      },
      {
        "text": "融",
        "label": "PER"
      }
    ]
  },
  {
    "sentence_id": "HCH_015_041_000017",
    "sentence": "在南與交阯太守卞展有舊，展於嶺南爲人所殺，融挺身奔赴。",
    "entities": [
      {
        "text": "交阯",
        "label": "LOC"
      },
      {
        "text": "太守",
        "label": "TITLE"
      },
      {
        "text": "卞展",
        "label": "PER"
      },
      {
        "text": "嶺南",
        "label": "LOC"
      }
    ]
  },
  {
    "sentence_id": "HCH_015_041_000018",
    "sentence": "舉秀才，對策中第，爲尚書殿中郎，不就，爲儀曹郎。",
    "entities": [
      {
        "text": "秀才",
        "label": "TITLE"
      },
      {
        "text": "尚書殿中郎",
        "label": "TITLE"
      },
      {
        "text": "儀曹郎",
        "label": "TITLE"
      }
    ]
  },
  {
    "sentence_id": "HCH_015_041_000019",
    "sentence": "泰始五年，明帝取荊、郢、湘、雍四州射手，叛者斬亡身及家長者，家口沒奚官。",
    "entities": [
      {
        "text": "泰始五年",
        "label": "TME"
      },
      {
        "text": "明帝",
        "label": "TITLE"
      },
      {
        "text": "荊",
        "label": "LOC"
      },
      {
        "text": "郢",
        "label": "LOC"
      },
      {
        "text": "湘",
        "label": "LOC"
      },
      {
        "text": "雍",
        "label": "LOC"
      },
      {
        "text": "四州",
        "label": "NUM"
      },
      {
        "text": "奚官",
        "label": "ORG"
      }
    ]
  },
  {
    "sentence_id": "HCH_015_041_000020",
    "sentence": "元徽初，郢州射手有叛者，融議家人家長罪所不及，亡身刑五年。",
    "entities": [
      {
        "text": "元徽",
        "label": "TME"
      },
      {
        "text": "郢州",
        "label": "LOC"
      },
      {
        "text": "融",
        "label": "PER"
      },
      {
        "text": "五年",
        "label": "TME"
      }
    ]
  },
  {
    "sentence_id": "HCH_015_041_000021",
    "sentence": "尋請假奔叔父喪，道中罰幹錢敬道鞭杖五十，寄繫延陵獄。",
    "entities": [
      {
        "text": "敬道",
        "label": "PER"
      },
      {
        "text": "延陵",
        "label": "LOC"
      }
    ]
  },
  {
    "sentence_id": "HCH_015_041_000022",
    "sentence": "大明五年制，二品清官行僮幹杖，不得出十。",
    "entities": [
      {
        "text": "大明五年",
        "label": "TME"
      },
      {
        "text": "二品",
        "label": "NUM"
      },
      {
        "text": "清官",
        "label": "TITLE"
      },
      {
        "text": "僮幹",
        "label": "TITLE"
      }
    ]
  },
  {
    "sentence_id": "HCH_015_041_000023",
    "sentence": "爲左丞孫緬所奏，免官。",
    "entities": [
      {
        "text": "左丞",
        "label": "TITLE"
      },
      {
        "text": "孫緬",
        "label": "PER"
      }
    ]
  },
  {
    "sentence_id": "HCH_015_041_000024",
    "sentence": "尋復位，攝祠、倉部二曹。",
    "entities": [
      {
        "text": "祠",
        "label": "TITLE"
      },
      {
        "text": "倉部",
        "label": "TITLE"
      }
    ]
  },
  {
    "sentence_id": "HCH_015_041_000025",
    "sentence": "領軍劉勉戰死，祠曹議「上應哭勉不」，融議「宜哭」。",
    "entities": [
      {
        "text": "領軍",
        "label": "TITLE"
      },
      {
        "text": "劉勉",
        "label": "PER"
      },
      {
        "text": "祠曹",
        "label": "TITLE"
      },
      {
        "text": "融",
        "label": "PER"
      }
    ]
  },
  {
    "sentence_id": "HCH_015_041_000026",
    "sentence": "於是始舉哀。",
    "entities": []
  },
  {
    "sentence_id": "HCH_015_041_000027",
    "sentence": "倉曹又以「正月俗人所忌，太倉爲可開不」，融議「不宜拘束小忌」。",
    "entities": [
      {
        "text": "倉曹",
        "label": "TITLE"
      },
      {
        "text": "正月",
        "label": "TME"
      },
      {
        "text": "太倉",
        "label": "LOC"
      },
      {
        "text": "融",
        "label": "PER"
      }
    ]
  },
  {
    "sentence_id": "HCH_015_041_000028",
    "sentence": "尋兼掌正廚，融見宰殺，回車徑去，自表解職。",
    "entities": [
      {
        "text": "尋兼",
        "label": "TITLE"
      },
      {
        "text": "正廚",
        "label": "TITLE"
      },
      {
        "text": "融",
        "label": "PER"
      }
    ]
  },
  {
    "sentence_id": "HCH_015_041_000029",
    "sentence": "爲安成王撫軍倉曹參軍，轉南陽王友。",
    "entities": [
      {
        "text": "安成王",
        "label": "TITLE"
      },
      {
        "text": "撫軍倉曹參軍",
        "label": "TITLE"
      },
      {
        "text": "南陽王",
        "label": "TITLE"
      }
    ]
  },
  {
    "sentence_id": "HCH_015_041_000030",
    "sentence": "融父暢先爲丞相長史，義宣事難，暢爲王玄謨所錄，將殺之。",
    "entities": [
      {
        "text": "融",
        "label": "PER"
      },
      {
        "text": "暢",
        "label": "PER"
      },
      {
        "text": "丞相長史",
        "label": "TITLE"
      },
      {
        "text": "義宣",
        "label": "ORG"
      },
      {
        "text": "王玄謨",
        "label": "PER"
      }
    ]
  },
  {
    "sentence_id": "HCH_015_041_000031",
    "sentence": "玄謨子瞻爲南陽王前軍長史，融啓求去官，不許。",
    "entities": [
      {
        "text": "玄謨",
        "label": "PER"
      },
      {
        "text": "南陽王",
        "label": "TITLE"
      },
      {
        "text": "融",
        "label": "PER"
      }
    ]
  },
  {
    "sentence_id": "HCH_015_041_000032",
    "sentence": "融家貧願祿，初與從叔征北將軍永書曰：「融昔稱幼學，早訓家風，雖則不敏，率以成性。布衣葦席，弱年所安，簞食瓢飲，不覺不樂。但世業清貧，民生多待，榛栗棗脩，女贄旣長，束帛禽鳥，男禮已大。勉身就官，十年七仕，不欲代耕，何至此事。昔求三吳一丞，雖屢舛錯。今聞南康缺守，願得爲之。融不知階級，階級亦可不知，融政以求丞不得，所以求郡，求郡不得，亦可復求丞。」",
    "entities": [
      {
        "text": "融",
        "label": "PER"
      },
      {
        "text": "從叔",
        "label": "ORG"
      },
      {
        "text": "征北將軍",
        "label": "TITLE"
      },
      {
        "text": "永",
        "label": "PER"
      },
      {
        "text": "十年七",
        "label": "TME"
      },
      {
        "text": "三吳",
        "label": "LOC"
      },
      {
        "text": "丞",
        "label": "TITLE"
      },
      {
        "text": "南康",
        "label": "LOC"
      }
    ]
  },
  {
    "sentence_id": "HCH_015_041_000033",
    "sentence": "又與吏部尚書王僧虔書曰：「融，天地之逸民也。進不辨貴，退不知賤，兀然造化，忽如草木。實以家貧累積，孤寡傷心，八姪俱孤，二弟頗弱，撫之而感，古人以悲。豈能山海陋祿，申融情累。阮籍愛東平土風，融亦欣晉平閑外。」",
    "entities": [
      {
        "text": "王僧虔",
        "label": "PER"
      },
      {
        "text": "融",
        "label": "PER"
      },
      {
        "text": "天地",
        "label": "LOC"
      },
      {
        "text": "貴",
        "label": "TITLE"
      },
      {
        "text": "賤",
        "label": "TITLE"
      },
      {
        "text": "兀然",
        "label": "TITLE"
      },
      {
        "text": "草木",
        "label": "LOC"
      },
      {
        "text": "家貧",
        "label": "TITLE"
      },
      {
        "text": "孤寡",
        "label": "TITLE"
      },
      {
        "text": "八姪",
        "label": "NUM"
      },
      {
        "text": "二弟",
        "label": "NUM"
      },
      {
        "text": "阮籍",
        "label": "PER"
      },
      {
        "text": "東平",
        "label": "LOC"
      },
      {
        "text": "晉平",
        "label": "LOC"
      }
    ]
  },
  {
    "sentence_id": "HCH_015_041_000034",
    "sentence": "時議以融非治民才，竟不果。",
    "entities": []
  },
  {
    "sentence_id": "HCH_015_041_000035",
    "sentence": "辟太祖太傅掾，歷驃騎豫章王司空諮議參軍，遷中書郎，非所好，乞爲中散大夫，不許。",
    "entities": [
      {
        "text": "太祖",
        "label": "TITLE"
      },
      {
        "text": "太傅",
        "label": "TITLE"
      },
      {
        "text": "驃騎豫章王",
        "label": "TITLE"
      },
      {
        "text": "司空諮議參軍",
        "label": "TITLE"
      },
      {
        "text": "中書郎",
        "label": "TITLE"
      },
      {
        "text": "中散大夫",
        "label": "TITLE"
      }
    ]
  },
  {
    "sentence_id": "HCH_015_041_000036",
    "sentence": "融風止詭越，坐常危膝，行則曳步，翹身仰首，意制甚多。",
    "entities": [
      {
        "text": "融",
        "label": "PER"
      }
    ]
  },
  {
    "sentence_id": "HCH_015_041_000037",
    "sentence": "隨例同行，常稽遲不進。",
    "entities": []
  },
  {
    "sentence_id": "HCH_015_041_000038",
    "sentence": "太祖素奇愛融，爲太尉時，時與融款接，見融常笑曰：「此人不可無一，不可有二。」",
    "entities": [
      {
        "text": "太祖",
        "label": "TITLE"
      },
      {
        "text": "融",
        "label": "PER"
      },
      {
        "text": "太尉",
        "label": "TITLE"
      }
    ]
  },
  {
    "sentence_id": "HCH_015_041_000039",
    "sentence": "卽位後，手詔賜融衣曰：「見卿衣服麤故，誠乃素懷有本；交爾藍縷，亦虧朝望。今送一通故衣，意謂雖故，乃勝新也。是吾所著，已令裁減稱卿之體。幷履一量。」",
    "entities": [
      {
        "text": "卽位",
        "label": "TME"
      },
      {
        "text": "融",
        "label": "PER"
      },
      {
        "text": "衣",
        "label": "NUM"
      },
      {
        "text": "藍縷",
        "label": "NUM"
      },
      {
        "text": "朝望",
        "label": "TITLE"
      },
      {
        "text": "故衣",
        "label": "NUM"
      },
      {
        "text": "幷履",
        "label": "NUM"
      }
    ]
  },
  {
    "sentence_id": "HCH_015_041_000040",
    "sentence": "融與吏部尚書何戢善，往詣戢，誤通尚書劉澄。",
    "entities": [
      {
        "text": "融",
        "label": "PER"
      },
      {
        "text": "吏部尚書",
        "label": "TITLE"
      },
      {
        "text": "何戢",
        "label": "PER"
      },
      {
        "text": "劉澄",
        "label": "PER"
      }
    ]
  },
  {
    "sentence_id": "HCH_015_041_000041",
    "sentence": "融下車入門，乃曰：「非是。」",
    "entities": [
      {
        "text": "融",
        "label": "PER"
      }
    ]
  },
  {
    "sentence_id": "HCH_015_041_000042",
    "sentence": "至戶外，望澄，又曰：「非是。」",
    "entities": [
      {
        "text": "澄",
        "label": "PER"
      }
    ]
  },
  {
    "sentence_id": "HCH_015_041_000043",
    "sentence": "旣造席，視澄曰：「都自非是。」",
    "entities": [
      {
        "text": "澄",
        "label": "PER"
      }
    ]
  },
  {
    "sentence_id": "HCH_015_041_000044",
    "sentence": "乃去。",
    "entities": []
  },
  {
    "sentence_id": "HCH_015_041_000045",
    "sentence": "其爲異如此。",
    "entities": []
  },
  {
    "sentence_id": "HCH_015_041_000046",
    "sentence": "又爲長沙王鎮軍、竟陵王征北諮議，竝領記室，司徒從事中郎。",
    "entities": [
      {
        "text": "長沙王",
        "label": "TITLE"
      },
      {
        "text": "鎮軍",
        "label": "TITLE"
      },
      {
        "text": "竟陵王",
        "label": "TITLE"
      },
      {
        "text": "征北諮議",
        "label": "TITLE"
      },
      {
        "text": "記室",
        "label": "TITLE"
      },
      {
        "text": "司徒",
        "label": "ORG"
      },
      {
        "text": "從事中郎",
        "label": "TITLE"
      }
    ]
  },
  {
    "sentence_id": "HCH_015_041_000047",
    "sentence": "永明二年，總明觀講，敕朝臣集聽。",
    "entities": [
      {
        "text": "永明二年",
        "label": "TME"
      },
      {
        "text": "總明觀",
        "label": "LOC"
      }
    ]
  },
  {
    "sentence_id": "HCH_015_041_000048",
    "sentence": "融扶入就榻，私索酒飲之，難問旣畢，乃長嘆曰：「嗚呼！仲尼獨何人哉！」",
    "entities": [
      {
        "text": "融",
        "label": "PER"
      },
      {
        "text": "仲尼",
        "label": "PER"
      }
    ]
  },
  {
    "sentence_id": "HCH_015_041_000049",
    "sentence": "爲御史中丞到撝所奏，免官，尋復。",
    "entities": [
      {
        "text": "御史中丞",
        "label": "TITLE"
      },
      {
        "text": "到撝",
        "label": "PER"
      }
    ]
  },
  {
    "sentence_id": "HCH_015_041_000050",
    "sentence": "融形貌短醜，精神清澈。",
    "entities": [
      {
        "text": "融",
        "label": "PER"
      }
    ]
  },
  {
    "sentence_id": "HCH_015_041_000051",
    "sentence": "王敬則見融革帶垂寬，殆將至骼，謂之曰：「革帶太急。」",
    "entities": [
      {
        "text": "王敬則",
        "label": "PER"
      },
      {
        "text": "融",
        "label": "PER"
      }
    ]
  },
  {
    "sentence_id": "HCH_015_041_000052",
    "sentence": "融曰：「旣非步吏，急帶何爲？」",
    "entities": [
      {
        "text": "融",
        "label": "PER"
      }
    ]
  },
  {
    "sentence_id": "HCH_015_041_000053",
    "sentence": "融假東出，世祖問融住在何處？",
    "entities": [
      {
        "text": "融",
        "label": "PER"
      },
      {
        "text": "東",
        "label": "LOC"
      },
      {
        "text": "世祖",
        "label": "TITLE"
      }
    ]
  },
  {
    "sentence_id": "HCH_015_041_000054",
    "sentence": "融答曰：「臣陸處無屋，舟居非水。」",
    "entities": [
      {
        "text": "融",
        "label": "PER"
      },
      {
        "text": "陸處",
        "label": "LOC"
      },
      {
        "text": "舟居",
        "label": "LOC"
      }
    ]
  },
  {
    "sentence_id": "HCH_015_041_000055",
    "sentence": "後日上以問融從兄緒，緒曰：「融近東出，未有居止，權牽小船，於岸上住。」",
    "entities": [
      {
        "text": "融",
        "label": "PER"
      },
      {
        "text": "從兄緒",
        "label": "PER"
      },
      {
        "text": "東",
        "label": "LOC"
      },
      {
        "text": "小船",
        "label": "NUM"
      },
      {
        "text": "岸",
        "label": "LOC"
      }
    ]
  },
  {
    "sentence_id": "HCH_015_041_000056",
    "sentence": "上大笑。",
    "entities": []
  },
  {
    "sentence_id": "HCH_015_041_000057",
    "sentence": "虜中聞融名，上使融接北使李道固，就席，道固顧之而言曰：「張融是宋彭城長史張暢子不？」",
    "entities": [
      {
        "text": "李道固",
        "label": "PER"
      },
      {
        "text": "張融",
        "label": "PER"
      },
      {
        "text": "宋",
        "label": "ORG"
      },
      {
        "text": "彭城",
        "label": "LOC"
      },
      {
        "text": "長史",
        "label": "TITLE"
      },
      {
        "text": "張暢",
        "label": "PER"
      }
    ]
  },
  {
    "sentence_id": "HCH_015_041_000058",
    "sentence": "融嚬蹙久之，曰：「先君不幸，名達六夷。」",
    "entities": [
      {
        "text": "融",
        "label": "PER"
      },
      {
        "text": "六夷",
        "label": "ORG"
      }
    ]
  },
  {
    "sentence_id": "HCH_015_041_000059",
    "sentence": "豫章王大會賔僚，融食炙始行畢，行炙人便去，融欲求鹽蒜，口終不言，方搖食指，半日乃息。",
    "entities": [
      {
        "text": "豫章王",
        "label": "TITLE"
      },
      {
        "text": "融",
        "label": "PER"
      },
      {
        "text": "半日",
        "label": "NUM"
      }
    ]
  },
  {
    "sentence_id": "HCH_015_041_000060",
    "sentence": "出入朝廷皆拭目驚觀之。",
    "entities": []
  },
  {
    "sentence_id": "HCH_015_041_000061",
    "sentence": "八年，朝臣賀衆瑞公事，融扶入拜起，復爲有司所奏，見原。",
    "entities": [
      {
        "text": "八年",
        "label": "TME"
      },
      {
        "text": "朝臣",
        "label": "ORG"
      },
      {
        "text": "衆瑞",
        "label": "TITLE"
      },
      {
        "text": "融",
        "label": "PER"
      }
    ]
  },
  {
    "sentence_id": "HCH_015_041_000062",
    "sentence": "遷司徒右長史。",
    "entities": [
      {
        "text": "司徒右長史",
        "label": "TITLE"
      }
    ]
  },
  {
    "sentence_id": "HCH_015_041_000063",
    "sentence": "竟陵張欣時爲諸暨令，坐罪當死。",
    "entities": [
      {
        "text": "竟陵",
        "label": "LOC"
      },
      {
        "text": "張欣時",
        "label": "PER"
      },
      {
        "text": "諸暨",
        "label": "LOC"
      },
      {
        "text": "令",
        "label": "TITLE"
      }
    ]
  },
  {
    "sentence_id": "HCH_015_041_000064",
    "sentence": "欣時父興世宋世討南譙王義宣，官軍欲殺融父暢，興世以袍覆暢而坐之，以此得免。",
    "entities": [
      {
        "text": "欣時",
        "label": "PER"
      },
      {
        "text": "興世",
        "label": "PER"
      },
      {
        "text": "宋",
        "label": "ORG"
      },
      {
        "text": "南譙王",
        "label": "TITLE"
      },
      {
        "text": "義宣",
        "label": "PER"
      },
      {
        "text": "融父",
        "label": "PER"
      },
      {
        "text": "暢",
        "label": "PER"
      }
    ]
  },
  {
    "sentence_id": "HCH_015_041_000065",
    "sentence": "興世卒，融著高履負土成墳。",
    "entities": [
      {
        "text": "興世",
        "label": "PER"
      },
      {
        "text": "融",
        "label": "PER"
      },
      {
        "text": "墳",
        "label": "LOC"
      }
    ]
  },
  {
    "sentence_id": "HCH_015_041_000066",
    "sentence": "至是融啓竟陵王子良，乞代欣時死。",
    "entities": [
      {
        "text": "融",
        "label": "PER"
      },
      {
        "text": "竟陵王",
        "label": "TITLE"
      },
      {
        "text": "子良",
        "label": "PER"
      },
      {
        "text": "欣時",
        "label": "PER"
      }
    ]
  },
  {
    "sentence_id": "HCH_015_041_000067",
    "sentence": "子良答曰：「此乃是長史美事，恐朝有常典，不得如長史所懷。」",
    "entities": [
      {
        "text": "子良",
        "label": "PER"
      },
      {
        "text": "長史",
        "label": "TITLE"
      }
    ]
  },
  {
    "sentence_id": "HCH_015_041_000068",
    "sentence": "遷黃門郎，太子中庶子，司徒左長史。",
    "entities": [
      {
        "text": "黃門郎",
        "label": "TITLE"
      },
      {
        "text": "太子中庶子",
        "label": "TITLE"
      },
      {
        "text": "司徒左長史",
        "label": "TITLE"
      }
    ]
  },
  {
    "sentence_id": "HCH_015_041_000069",
    "sentence": "融有孝義，忌月三旬不聽樂，事嫂甚謹。",
    "entities": [
      {
        "text": "融",
        "label": "PER"
      },
      {
        "text": "嫂",
        "label": "PER"
      }
    ]
  },
  {
    "sentence_id": "HCH_015_041_000070",
    "sentence": "宋丞相義宣起事，父暢以不同將見殺，司馬竺超民諫免之。",
    "entities": [
      {
        "text": "宋",
        "label": "ORG"
      },
      {
        "text": "丞相",
        "label": "TITLE"
      },
      {
        "text": "義宣",
        "label": "PER"
      },
      {
        "text": "父暢",
        "label": "PER"
      },
      {
        "text": "司馬",
        "label": "TITLE"
      },
      {
        "text": "竺超民",
        "label": "PER"
      }
    ]
  },
  {
    "sentence_id": "HCH_015_041_000071",
    "sentence": "暢臨終謂諸子曰：「昔丞相事難，吾緣竺司馬得活，爾等必報其子弟。」",
    "entities": [
      {
        "text": "暢",
        "label": "PER"
      },
      {
        "text": "丞相",
        "label": "TITLE"
      },
      {
        "text": "竺司馬",
        "label": "TITLE"
      }
    ]
  },
  {
    "sentence_id": "HCH_015_041_000072",
    "sentence": "後超民孫微冬月遭母喪，居貧，融往弔之，悉脫衣以爲賻，披牛被而反。",
    "entities": [
      {
        "text": "超民",
        "label": "PER"
      },
      {
        "text": "孫微",
        "label": "PER"
      },
      {
        "text": "冬月",
        "label": "TME"
      },
      {
        "text": "融",
        "label": "PER"
      },
      {
        "text": "牛被",
        "label": "LOC"
      }
    ]
  },
  {
    "sentence_id": "HCH_015_041_000073",
    "sentence": "常以兄事微。",
    "entities": [
      {
        "text": "微",
        "label": "PER"
      }
    ]
  },
  {
    "sentence_id": "HCH_015_041_000074",
    "sentence": "豫章王嶷、竟陵王子良薨，自以身經佐吏，哭輙盡慟。",
    "entities": [
      {
        "text": "豫章王",
        "label": "TITLE"
      },
      {
        "text": "嶷",
        "label": "PER"
      },
      {
        "text": "竟陵王",
        "label": "TITLE"
      },
      {
        "text": "子良",
        "label": "PER"
      }
    ]
  },
  {
    "sentence_id": "HCH_015_041_000075",
    "sentence": "建武四年，病卒。",
    "entities": [
      {
        "text": "建武四年",
        "label": "TME"
      }
    ]
  },
  {
    "sentence_id": "HCH_015_041_000076",
    "sentence": "年五十四。",
    "entities": [
      {
        "text": "年五十四",
        "label": "NUM"
      }
    ]
  },
  {
    "sentence_id": "HCH_015_041_000077",
    "sentence": "遺令建白旌無旒，不設祭，令人捉麈尾登屋復魂。",
    "entities": [
      {
        "text": "白旌",
        "label": "TITLE"
      },
      {
        "text": "麈尾",
        "label": "TITLE"
      }
    ]
  },
  {
    "sentence_id": "HCH_015_041_000078",
    "sentence": "曰：「吾生平所善，自當凌雲一笑。三千買棺，無製新衾。左手執《孝經》、《老子》，右手執小品《法華經》。妾二人，哀事畢，各遣還家。」",
    "entities": [
      {
        "text": "孝經",
        "label": "TITLE"
      },
      {
        "text": "老子",
        "label": "TITLE"
      },
      {
        "text": "小品",
        "label": "TITLE"
      },
      {
        "text": "法華經",
        "label": "TITLE"
      },
      {
        "text": "二人",
        "label": "NUM"
      }
    ]
  },
  {
    "sentence_id": "HCH_015_041_000079",
    "sentence": "又曰：「以吾平生之風調，何至使婦人行哭失聲，不須暫停閨閤。」",
    "entities": [
      {
        "text": "婦人",
        "label": "PER"
      },
      {
        "text": "閨閤",
        "label": "LOC"
      }
    ]
  },
  {
    "sentence_id": "HCH_015_041_000080",
    "sentence": "融玄義無師法，而神解過人，白黑談論，鮮能抗拒。",
    "entities": [
      {
        "text": "融",
        "label": "PER"
      },
      {
        "text": "白黑",
        "label": "ORG"
      }
    ]
  },
  {
    "sentence_id": "HCH_015_041_000081",
    "sentence": "永明中，遇疾，爲《門律自序》曰：「吾文章之體，多爲世人所驚，汝可師耳以心，不可使耳爲心師也。夫文豈有常體，但以有體爲常，政當使常有其體。丈夫當刪《詩》《書》，制禮樂，何至因循寄人籬下。且中代之文，道體闕變，尺寸相資，彌縫舊物。吾之文章，體亦何異，何嘗顛溫敘而錯寒暑，綜哀樂而橫歌哭哉？政以屬辭多出，比事不羈，不阡不陌，非途非路耳。然其傳音振逸，鳴節竦韻，或當未極，亦已極其所矣。汝若復別得體者，吾不拘也。吾義亦如文，造次乘我，顛沛非物。吾無師無友，不文不句，頗有孤神獨逸耳。義之爲用，將使性入清波，塵洗猶沐。無得釣聲同利，舉價如高，俾是道場，險成軍路。吾昔嗜僧言，多肆法辯，此盡遊乎言笑，而汝等無幸。」",
    "entities": [
      {
        "text": "永明",
        "label": "TME"
      },
      {
        "text": "詩",
        "label": "TITLE"
      },
      {
        "text": "書",
        "label": "TITLE"
      },
      {
        "text": "禮樂",
        "label": "TITLE"
      },
      {
        "text": "中代",
        "label": "LOC"
      },
      {
        "text": "義",
        "label": "TITLE"
      },
      {
        "text": "性",
        "label": "TITLE"
      },
      {
        "text": "清波",
        "label": "LOC"
      },
      {
        "text": "塵",
        "label": "TITLE"
      },
      {
        "text": "道場",
        "label": "ORG"
      },
      {
        "text": "軍路",
        "label": "ORG"
      }
    ]
  },
  {
    "sentence_id": "HCH_015_041_000082",
    "sentence": "又云：「人生之口，正可論道說義，惟飲與食。此外如樹網焉。吾每以不爾爲恨，爾曹當振綱也。」",
    "entities": [
      {
        "text": "又云",
        "label": "TME"
      },
      {
        "text": "口",
        "label": "NUM"
      },
      {
        "text": "飲與食",
        "label": "NUM"
      }
    ]
  },
  {
    "sentence_id": "HCH_015_041_000083",
    "sentence": "臨卒，又戒其子曰：「手澤存焉，父書不讀！況父音情，婉在其韻。吾意不然，別遺爾音。吾文體英絕，變而屢奇，旣不能遠至漢魏，故無取嗟晉宋。豈吾天挺，蓋不隤家聲。汝若不看，父祖之意欲汝見也。可號哭而看之。」",
    "entities": [
      {
        "text": "臨卒",
        "label": "TME"
      },
      {
        "text": "其子",
        "label": "PER"
      },
      {
        "text": "父書",
        "label": "TITLE"
      },
      {
        "text": "父音情",
        "label": "TITLE"
      },
      {
        "text": "漢魏",
        "label": "LOC"
      },
      {
        "text": "晉宋",
        "label": "LOC"
      },
      {
        "text": "天挺",
        "label": "TITLE"
      },
      {
        "text": "家聲",
        "label": "TITLE"
      },
      {
        "text": "父祖",
        "label": "PER"
      }
    ]
  },
  {
    "sentence_id": "HCH_015_041_000084",
    "sentence": "融自名集爲《玉海》。",
    "entities": [
      {
        "text": "融",
        "label": "PER"
      },
      {
        "text": "集爲",
        "label": "PER"
      },
      {
        "text": "玉海",
        "label": "TITLE"
      }
    ]
  },
  {
    "sentence_id": "HCH_015_041_000085",
    "sentence": "司徒褚淵問《玉海》名，融答：「玉以比德，海崇上善。」",
    "entities": [
      {
        "text": "司徒",
        "label": "TITLE"
      },
      {
        "text": "褚淵",
        "label": "PER"
      },
      {
        "text": "玉海",
        "label": "TITLE"
      },
      {
        "text": "融",
        "label": "PER"
      }
    ]
  },
  {
    "sentence_id": "HCH_015_041_000086",
    "sentence": "文集數十卷行於世。",
    "entities": [
      {
        "text": "文集",
        "label": "TITLE"
      },
      {
        "text": "數十卷",
        "label": "NUM"
      }
    ]
  },
  {
    "sentence_id": "HCH_015_041_000087",
    "sentence": "張氏知名，前有敷、演、鏡、暢，後有充、融、卷、稷。",
    "entities": [
      {
        "text": "張氏",
        "label": "ORG"
      },
      {
        "text": "敷",
        "label": "PER"
      },
      {
        "text": "演",
        "label": "PER"
      },
      {
        "text": "鏡",
        "label": "PER"
      },
      {
        "text": "暢",
        "label": "PER"
      },
      {
        "text": "充",
        "label": "PER"
      },
      {
        "text": "融",
        "label": "PER"
      },
      {
        "text": "卷",
        "label": "PER"
      },
      {
        "text": "稷",
        "label": "PER"
      }
    ]
  },
  {
    "sentence_id": "HCH_015_041_000088",
    "sentence": "周顒字彥倫，汝南安城人。",
    "entities": [
      {
        "text": "周顒",
        "label": "PER"
      },
      {
        "text": "彥倫",
        "label": "PER"
      },
      {
        "text": "汝南",
        "label": "LOC"
      },
      {
        "text": "安城",
        "label": "LOC"
      }
    ]
  },
  {
    "sentence_id": "HCH_015_041_000089",
    "sentence": "晉左光祿大夫顗七世孫也。",
    "entities": [
      {
        "text": "晉",
        "label": "ORG"
      },
      {
        "text": "左光祿大夫",
        "label": "TITLE"
      },
      {
        "text": "顗",
        "label": "PER"
      },
      {
        "text": "七世",
        "label": "NUM"
      }
    ]
  },
  {
    "sentence_id": "HCH_015_041_000090",
    "sentence": "祖虎頭，員外常侍。",
    "entities": [
      {
        "text": "祖虎頭",
        "label": "PER"
      },
      {
        "text": "員外常侍",
        "label": "TITLE"
      }
    ]
  },
  {
    "sentence_id": "HCH_015_041_000091",
    "sentence": "父恂，歸郷相。",
    "entities": [
      {
        "text": "恂",
        "label": "PER"
      },
      {
        "text": "歸郷相",
        "label": "TITLE"
      }
    ]
  },
  {
    "sentence_id": "HCH_015_041_000092",
    "sentence": "顒少爲族祖朗所知。",
    "entities": [
      {
        "text": "顒",
        "label": "PER"
      },
      {
        "text": "族祖",
        "label": "TITLE"
      },
      {
        "text": "朗",
        "label": "PER"
      }
    ]
  },
  {
    "sentence_id": "HCH_015_041_000093",
    "sentence": "解褐海陵國侍郎。",
    "entities": [
      {
        "text": "海陵國",
        "label": "LOC"
      },
      {
        "text": "侍郎",
        "label": "TITLE"
      }
    ]
  },
  {
    "sentence_id": "HCH_015_041_000094",
    "sentence": "益州刺史蕭惠開賞異顒，攜入蜀，爲厲鋒將軍，帶肥郷、成都二縣令。",
    "entities": [
      {
        "text": "益州",
        "label": "LOC"
      },
      {
        "text": "刺史",
        "label": "TITLE"
      },
      {
        "text": "蕭惠開",
        "label": "PER"
      },
      {
        "text": "厲鋒將軍",
        "label": "TITLE"
      },
      {
        "text": "肥郷",
        "label": "LOC"
      },
      {
        "text": "成都",
        "label": "LOC"
      },
      {
        "text": "二縣",
        "label": "NUM"
      }
    ]
  },
  {
    "sentence_id": "HCH_015_041_000095",
    "sentence": "轉惠開輔國府參軍，將軍、令如故。",
    "entities": [
      {
        "text": "惠開",
        "label": "PER"
      },
      {
        "text": "輔國府參軍",
        "label": "TITLE"
      }
    ]
  },
  {
    "sentence_id": "HCH_015_041_000096",
    "sentence": "仍爲府主簿。",
    "entities": []
  },
  {
    "sentence_id": "HCH_015_041_000097",
    "sentence": "常謂惠開性太險峻，每致諫，惠開不悅，答顒曰：「天險地險，王公設險，但問用險何如耳。」",
    "entities": [
      {
        "text": "惠開",
        "label": "PER"
      },
      {
        "text": "顒",
        "label": "PER"
      },
      {
        "text": "天險",
        "label": "LOC"
      },
      {
        "text": "地險",
        "label": "LOC"
      },
      {
        "text": "王公",
        "label": "TITLE"
      }
    ]
  },
  {
    "sentence_id": "HCH_015_041_000098",
    "sentence": "隨惠開還都。",
    "entities": [
      {
        "text": "惠開",
        "label": "PER"
      },
      {
        "text": "都",
        "label": "LOC"
      }
    ]
  },
  {
    "sentence_id": "HCH_015_041_000099",
    "sentence": "宋明帝頗好言理，以顒有辭義，引入殿內，親近宿直。",
    "entities": [
      {
        "text": "宋明帝",
        "label": "TITLE"
      },
      {
        "text": "顒",
        "label": "PER"
      }
    ]
  },
  {
    "sentence_id": "HCH_015_041_000100",
    "sentence": "帝所爲慘毒之事，顒不敢顯諫，輙誦經中因緣罪福事，帝亦爲之小止。",
    "entities": [
      {
        "text": "顒",
        "label": "PER"
      }
    ]
  },
  {
    "sentence_id": "HCH_015_041_000101",
    "sentence": "轉安成王撫軍行參軍。",
    "entities": [
      {
        "text": "安成王",
        "label": "TITLE"
      },
      {
        "text": "撫軍行參軍",
        "label": "TITLE"
      }
    ]
  },
  {
    "sentence_id": "HCH_015_041_000102",
    "sentence": "元徽初，出爲剡令，有恩惠，百姓思之。",
    "entities": [
      {
        "text": "元徽",
        "label": "TME"
      },
      {
        "text": "剡",
        "label": "LOC"
      }
    ]
  },
  {
    "sentence_id": "HCH_015_041_000103",
    "sentence": "還歷邵陵王南中郎三府參軍。",
    "entities": [
      {
        "text": "邵陵王",
        "label": "TITLE"
      },
      {
        "text": "南中郎",
        "label": "TITLE"
      },
      {
        "text": "三府",
        "label": "ORG"
      }
    ]
  },
  {
    "sentence_id": "HCH_015_041_000104",
    "sentence": "太祖輔政，引接顒。",
    "entities": [
      {
        "text": "太祖",
        "label": "TITLE"
      },
      {
        "text": "顒",
        "label": "PER"
      }
    ]
  },
  {
    "sentence_id": "HCH_015_041_000105",
    "sentence": "顒善尺牘，沈攸之送絕交書，太祖口授令顒裁答。",
    "entities": [
      {
        "text": "顒",
        "label": "PER"
      },
      {
        "text": "沈攸之",
        "label": "PER"
      },
      {
        "text": "絕交書",
        "label": "TITLE"
      },
      {
        "text": "太祖",
        "label": "TITLE"
      }
    ]
  },
  {
    "sentence_id": "HCH_015_041_000106",
    "sentence": "轉齊臺殿中郎。",
    "entities": [
      {
        "text": "齊臺",
        "label": "ORG"
      },
      {
        "text": "殿中郎",
        "label": "TITLE"
      }
    ]
  },
  {
    "sentence_id": "HCH_015_041_000107",
    "sentence": "建元初，爲長沙王參軍，後軍參軍，山陰令。",
    "entities": [
      {
        "text": "建元",
        "label": "TME"
      },
      {
        "text": "長沙王",
        "label": "TITLE"
      },
      {
        "text": "參軍",
        "label": "TITLE"
      },
      {
        "text": "後軍",
        "label": "TITLE"
      },
      {
        "text": "山陰",
        "label": "LOC"
      },
      {
        "text": "令",
        "label": "TITLE"
      }
    ]
  },
  {
    "sentence_id": "HCH_015_041_000108",
    "sentence": "縣舊訂滂民，以供雜使。",
    "entities": [
      {
        "text": "縣",
        "label": "LOC"
      },
      {
        "text": "滂民",
        "label": "ORG"
      }
    ]
  },
  {
    "sentence_id": "HCH_015_041_000109",
    "sentence": "顒言之於太守聞喜公子良曰：「竊見滂民之困，困實極矣。役命有常，祗應轉竭，蹙迫驅催，莫安其所。險者或竄避山湖，困者自經溝瀆爾。亦有摧臂斮手，苟自殘落，販傭貼子，權赴急難。每至滂使發動，遵赴常促，輙有柤杖被錄，稽顙階垂，泣涕告哀，不知所振。下官未嘗不臨食罷箸，當書偃筆，爲之久之，愴不能已。交事不濟，不得不就加捶罰，見此辛酸，時不可過。山陰邦治，事倍餘城；然略聞諸縣，亦處處皆躓。唯上虞以百戶一滂，大爲優足，過此列城，不無凋罄。宜應有以普救倒懸，設流開便，則轉患爲功，得之何遠。」",
    "entities": [
      {
        "text": "顒",
        "label": "PER"
      },
      {
        "text": "太守",
        "label": "TITLE"
      },
      {
        "text": "聞喜公",
        "label": "TITLE"
      },
      {
        "text": "子良",
        "label": "PER"
      },
      {
        "text": "山陰",
        "label": "LOC"
      },
      {
        "text": "上虞",
        "label": "LOC"
      },
      {
        "text": "百戶",
        "label": "NUM"
      },
      {
        "text": "倒懸",
        "label": "NUM"
      }
    ]
  },
  {
    "sentence_id": "HCH_015_041_000110",
    "sentence": "還爲文惠太子中軍錄事參軍，隨府轉征北。",
    "entities": [
      {
        "text": "文惠太子",
        "label": "TITLE"
      },
      {
        "text": "中軍錄事參軍",
        "label": "TITLE"
      },
      {
        "text": "征北",
        "label": "TITLE"
      }
    ]
  },
  {
    "sentence_id": "HCH_015_041_000111",
    "sentence": "文惠在東宮，顒還正員郎，始興王前軍諮議。",
    "entities": [
      {
        "text": "文惠",
        "label": "TITLE"
      },
      {
        "text": "顒",
        "label": "PER"
      },
      {
        "text": "正員郎",
        "label": "TITLE"
      },
      {
        "text": "始興王",
        "label": "TITLE"
      },
      {
        "text": "前軍諮議",
        "label": "TITLE"
      }
    ]
  },
  {
    "sentence_id": "HCH_015_041_000112",
    "sentence": "直侍殿省，復見賞遇。",
    "entities": [
      {
        "text": "殿省",
        "label": "ORG"
      }
    ]
  },
  {
    "sentence_id": "HCH_015_041_000113",
    "sentence": "顒音辭辯麗，出言不窮，宮商朱紫，發口成句。",
    "entities": [
      {
        "text": "顒",
        "label": "PER"
      },
      {
        "text": "宮商朱紫",
        "label": "TITLE"
      }
    ]
  },
  {
    "sentence_id": "HCH_015_041_000114",
    "sentence": "汎涉百家，長於佛理。",
    "entities": [
      {
        "text": "佛理",
        "label": "TITLE"
      }
    ]
  },
  {
    "sentence_id": "HCH_015_041_000115",
    "sentence": "著《三宗論》。",
    "entities": [
      {
        "text": "三宗論",
        "label": "TITLE"
      }
    ]
  },
  {
    "sentence_id": "HCH_015_041_000116",
    "sentence": "立空假名，立不空假名。",
    "entities": []
  },
  {
    "sentence_id": "HCH_015_041_000117",
    "sentence": "設不空假名難空假名，設空假名難不空假名。",
    "entities": [
      {
        "text": "難空假名",
        "label": "PER"
      },
      {
        "text": "難不空假名",
        "label": "PER"
      }
    ]
  },
  {
    "sentence_id": "HCH_015_041_000118",
    "sentence": "假名空難二宗，又立假名空。",
    "entities": [
      {
        "text": "假名",
        "label": "TITLE"
      },
      {
        "text": "空",
        "label": "PER"
      },
      {
        "text": "二宗",
        "label": "TITLE"
      }
    ]
  },
  {
    "sentence_id": "HCH_015_041_000119",
    "sentence": "西涼州智林道人遺顒書曰：「此義旨趣似非始開，妙聲中絕六七十載。貧道年二十時，便得此義，竊每歡喜，無與共之。年少見長安耆老，多云關中高勝乃舊有此義，當法集盛時，能深得斯趣者，本無多人。過江東略是無一。貧道捉麈尾來四十餘年，東西講說，謬重一時，餘義頗見宗錄，唯有此塗白黑無一人得者，爲之發病。非意此音猥來入耳，始是眞實行道第一功德。」",
    "entities": [
      {
        "text": "西涼州",
        "label": "LOC"
      },
      {
        "text": "智林道人",
        "label": "PER"
      },
      {
        "text": "顒",
        "label": "PER"
      },
      {
        "text": "年二十",
        "label": "NUM"
      },
      {
        "text": "長安",
        "label": "LOC"
      },
      {
        "text": "耆老",
        "label": "PER"
      },
      {
        "text": "關中",
        "label": "LOC"
      },
      {
        "text": "東",
        "label": "LOC"
      },
      {
        "text": "麈尾",
        "label": "TITLE"
      },
      {
        "text": "四十餘年",
        "label": "TME"
      },
      {
        "text": "一時",
        "label": "NUM"
      },
      {
        "text": "一人",
        "label": "NUM"
      },
      {
        "text": "第一",
        "label": "NUM"
      }
    ]
  },
  {
    "sentence_id": "HCH_015_041_000120",
    "sentence": "其論見重如此。",
    "entities": []
  },
  {
    "sentence_id": "HCH_015_041_000121",
    "sentence": "顒於鍾山西立隱舍，休沐則歸之。",
    "entities": [
      {
        "text": "顒",
        "label": "PER"
      },
      {
        "text": "鍾山",
        "label": "LOC"
      }
    ]
  },
  {
    "sentence_id": "HCH_015_041_000122",
    "sentence": "轉太子僕，兼著作，撰起居注。",
    "entities": [
      {
        "text": "太子僕",
        "label": "TITLE"
      },
      {
        "text": "著作",
        "label": "TITLE"
      },
      {
        "text": "起居注",
        "label": "TITLE"
      }
    ]
  },
  {
    "sentence_id": "HCH_015_041_000123",
    "sentence": "遷中書郎，兼著作如故。",
    "entities": [
      {
        "text": "中書郎",
        "label": "TITLE"
      },
      {
        "text": "著作",
        "label": "TITLE"
      }
    ]
  },
  {
    "sentence_id": "HCH_015_041_000124",
    "sentence": "常遊侍東宮。",
    "entities": [
      {
        "text": "東宮",
        "label": "LOC"
      }
    ]
  },
  {
    "sentence_id": "HCH_015_041_000125",
    "sentence": "少從外氏車騎將軍臧質家得衞恒散隷書法，學之甚工。",
    "entities": [
      {
        "text": "車騎將軍",
        "label": "TITLE"
      },
      {
        "text": "臧質",
        "label": "PER"
      },
      {
        "text": "衞恒",
        "label": "PER"
      },
      {
        "text": "散隷",
        "label": "TITLE"
      },
      {
        "text": "書法",
        "label": "TITLE"
      }
    ]
  },
  {
    "sentence_id": "HCH_015_041_000126",
    "sentence": "文惠太子使顒書玄圃茅齋壁，國子祭酒何胤以倒薤書求就顒換之，顒笑而答曰：「天下有道，丘不與易也。」",
    "entities": [
      {
        "text": "文惠太子",
        "label": "TITLE"
      },
      {
        "text": "顒",
        "label": "PER"
      },
      {
        "text": "玄圃",
        "label": "LOC"
      },
      {
        "text": "國子祭酒",
        "label": "TITLE"
      },
      {
        "text": "何胤",
        "label": "PER"
      },
      {
        "text": "倒薤書",
        "label": "TITLE"
      },
      {
        "text": "天下",
        "label": "LOC"
      },
      {
        "text": "丘",
        "label": "PER"
      }
    ]
  },
  {
    "sentence_id": "HCH_015_041_000127",
    "sentence": "每賔友會同，顒虛席晤語，辭韻如流，聽者忘倦。",
    "entities": [
      {
        "text": "顒",
        "label": "PER"
      }
    ]
  },
  {
    "sentence_id": "HCH_015_041_000128",
    "sentence": "兼善老、易，與張融相遇，輙以玄言相滯，彌日不解。",
    "entities": [
      {
        "text": "老",
        "label": "TITLE"
      },
      {
        "text": "易",
        "label": "TITLE"
      },
      {
        "text": "張融",
        "label": "PER"
      },
      {
        "text": "玄言",
        "label": "TITLE"
      }
    ]
  },
  {
    "sentence_id": "HCH_015_041_000129",
    "sentence": "清貧寡欲，終日長蔬食，雖有妻子，獨處山舍。",
    "entities": []
  },
  {
    "sentence_id": "HCH_015_041_000130",
    "sentence": "衞將軍王儉謂顒曰：「卿山中何所食？」",
    "entities": [
      {
        "text": "衞將軍",
        "label": "TITLE"
      },
      {
        "text": "王儉",
        "label": "PER"
      },
      {
        "text": "顒",
        "label": "PER"
      }
    ]
  },
  {
    "sentence_id": "HCH_015_041_000131",
    "sentence": "顒曰：「赤米白鹽，綠葵紫蓼。」",
    "entities": [
      {
        "text": "顒",
        "label": "PER"
      },
      {
        "text": "赤米",
        "label": "NUM"
      },
      {
        "text": "白鹽",
        "label": "NUM"
      },
      {
        "text": "綠葵",
        "label": "NUM"
      },
      {
        "text": "紫蓼",
        "label": "NUM"
      }
    ]
  },
  {
    "sentence_id": "HCH_015_041_000132",
    "sentence": "文惠太子問顒：「菜食何味最勝？」",
    "entities": [
      {
        "text": "文惠太子",
        "label": "TITLE"
      },
      {
        "text": "顒",
        "label": "PER"
      },
      {
        "text": "菜食",
        "label": "NUM"
      }
    ]
  },
  {
    "sentence_id": "HCH_015_041_000133",
    "sentence": "顒曰：「春初早韭，秋末晚菘。」",
    "entities": [
      {
        "text": "顒",
        "label": "PER"
      },
      {
        "text": "春初",
        "label": "TME"
      },
      {
        "text": "早韭",
        "label": "LOC"
      },
      {
        "text": "秋末",
        "label": "TME"
      },
      {
        "text": "晚菘",
        "label": "LOC"
      }
    ]
  },
  {
    "sentence_id": "HCH_015_041_000134",
    "sentence": "時何胤亦精信佛法，無妻妾。",
    "entities": [
      {
        "text": "何胤",
        "label": "PER"
      },
      {
        "text": "佛法",
        "label": "ORG"
      }
    ]
  },
  {
    "sentence_id": "HCH_015_041_000135",
    "sentence": "太子又問顒：「卿精進何如何胤？」",
    "entities": [
      {
        "text": "太子",
        "label": "TITLE"
      },
      {
        "text": "顒",
        "label": "PER"
      },
      {
        "text": "何胤",
        "label": "PER"
      }
    ]
  },
  {
    "sentence_id": "HCH_015_041_000136",
    "sentence": "顒曰：「三塗八難，共所未免。然各有其累。」",
    "entities": [
      {
        "text": "三塗",
        "label": "LOC"
      },
      {
        "text": "八難",
        "label": "TME"
      }
    ]
  },
  {
    "sentence_id": "HCH_015_041_000137",
    "sentence": "太子曰：「所累伊何？」",
    "entities": [
      {
        "text": "太子",
        "label": "TITLE"
      }
    ]
  },
  {
    "sentence_id": "HCH_015_041_000138",
    "sentence": "對曰：「周妻何肉。」",
    "entities": [
      {
        "text": "周妻",
        "label": "PER"
      },
      {
        "text": "何肉",
        "label": "PER"
      }
    ]
  },
  {
    "sentence_id": "HCH_015_041_000139",
    "sentence": "其言辭應變，皆如此也。",
    "entities": []
  },
  {
    "sentence_id": "HCH_015_041_000140",
    "sentence": "轉國子博士，兼著作如故。",
    "entities": [
      {
        "text": "國子博士",
        "label": "TITLE"
      },
      {
        "text": "著作",
        "label": "TITLE"
      }
    ]
  },
  {
    "sentence_id": "HCH_015_041_000141",
    "sentence": "太學諸生慕其風，爭事華辯。",
    "entities": [
      {
        "text": "太學",
        "label": "ORG"
      },
      {
        "text": "諸生",
        "label": "ORG"
      },
      {
        "text": "華辯",
        "label": "PER"
      }
    ]
  },
  {
    "sentence_id": "HCH_015_041_000142",
    "sentence": "後何胤言斷食生，猶欲食肉、白魚、脯、糖蟹，以爲非見生物。",
    "entities": [
      {
        "text": "何胤",
        "label": "PER"
      },
      {
        "text": "白魚",
        "label": "LOC"
      },
      {
        "text": "脯",
        "label": "NUM"
      },
      {
        "text": "糖蟹",
        "label": "LOC"
      }
    ]
  },
  {
    "sentence_id": "HCH_015_041_000143",
    "sentence": "疑食蚶蠣，使學生議之。",
    "entities": [
      {
        "text": "蚶蠣",
        "label": "NUM"
      }
    ]
  },
  {
    "sentence_id": "HCH_015_041_000144",
    "sentence": "學生鍾岏曰：「之就脯，驟於屈伸，蟹之將糖，躁擾彌甚。仁人用意，深懷如怛。至於車螯蚶蠣，眉目內闕，慚渾沌之奇，礦殼外緘，非金人之慎。不悴不榮，曾草木之不若；無馨無臭，與瓦礫其何算。故宜長充庖廚，永爲口實。」",
    "entities": [
      {
        "text": "學生鍾岏",
        "label": "TITLE"
      },
      {
        "text": "脯",
        "label": "NUM"
      },
      {
        "text": "蟹",
        "label": "NUM"
      },
      {
        "text": "糖",
        "label": "NUM"
      },
      {
        "text": "車螯",
        "label": "NUM"
      },
      {
        "text": "蚶蠣",
        "label": "NUM"
      }
    ]
  },
  {
    "sentence_id": "HCH_015_041_000145",
    "sentence": "竟陵王子良見岏議，大怒。",
    "entities": [
      {
        "text": "竟陵王",
        "label": "TITLE"
      },
      {
        "text": "子良",
        "label": "PER"
      },
      {
        "text": "岏",
        "label": "PER"
      }
    ]
  },
  {
    "sentence_id": "HCH_015_041_000146",
    "sentence": "胤兄點，亦遁節清信。",
    "entities": [
      {
        "text": "胤",
        "label": "PER"
      },
      {
        "text": "點",
        "label": "PER"
      }
    ]
  },
  {
    "sentence_id": "HCH_015_041_000147",
    "sentence": "顒與書，勸令菜食。",
    "entities": [
      {
        "text": "顒",
        "label": "PER"
      },
      {
        "text": "書",
        "label": "TITLE"
      }
    ]
  },
  {
    "sentence_id": "HCH_015_041_000148",
    "sentence": "曰：「丈人之所以未極遐蹈，或在不近全菜邪？脫灑離析之討，鼎俎網罟之興，載之簡策，其來寔遠。誰敢干議？觀聖人之設膳脩，仍復爲之品節，蓋以茹毛飲血，與生民共始，縱而勿裁，將無畔。善爲士者，豈不以恕己爲懷？是以各靜封疆，罔相陵軼。況乃變之大者，莫過死生；生之所重，無踰性命。性命之於彼極切，滋味之在我可賒，而終身朝晡，資之以永歲，彼就冤殘，莫能自列，我業久長，吁哉可畏。且區區微卵，脆薄易矝，歂彼弱麑，顧步宜衄。觀其飲喙飛沈，使人憐悼，況可心心撲褫，加復恣忍吞嚼。至乃野牧盛羣，閉豢重圈，量肉揣毛，以俟枝剝，如土委地，僉謂常理，可爲愴息，事豈一塗。若云三世理誣，則幸矣良快，如使此道果然，而受形未息，則一往一來，一生一死，輪迴是常事。雜報如家，人天如客，遇客日尠，在家日多，吾儕信業，未足長免，則傷心之慘，行亦自及。丈人於血氣之類，雖無身踐，至於晨鳧夜鯉，不能不取備屠門。財貝之一經盜手，猶爲廉士所棄；生性之一啓鸞刀，寧復慈心所忍。騶虞雖飢，非自死之草不食，聞其風豈不使人多愧。衆生之稟此形質，以畜肌膋，皆由其積壅癡迷，沈流莫反，報受穢濁，歷苦酸長，此甘與肥，皆無明之報聚也。何至復引此滋腴，自汙腸胃。丈人得此有素，",
    "entities": [
      {
        "text": "丈人",
        "label": "TITLE"
      },
      {
        "text": "聖人",
        "label": "PER"
      },
      {
        "text": "三世",
        "label": "NUM"
      },
      {
        "text": "騶虞",
        "label": "ORG"
      },
      {
        "text": "衆生",
        "label": "ORG"
      }
    ]
  },
  {
    "sentence_id": "HCH_015_041_000149",
    "sentence": "聊復寸言發起耳。",
    "entities": []
  },
  {
    "sentence_id": "HCH_015_041_000150",
    "sentence": "顒卒官時，會王儉講《孝經》未畢，舉曇濟自代，學者榮之。",
    "entities": [
      {
        "text": "顒",
        "label": "PER"
      },
      {
        "text": "王儉",
        "label": "PER"
      },
      {
        "text": "曇濟",
        "label": "PER"
      }
    ]
  },
  {
    "sentence_id": "HCH_015_041_000151",
    "sentence": "官爲給事中。",
    "entities": [
      {
        "text": "給事中",
        "label": "TITLE"
      }
    ]
  },
  {
    "sentence_id": "HCH_015_041_000152",
    "sentence": "史臣曰：弘毅存容，至仁表貌，汲黯剛戇，崔琰聲姿，然後能不憚雄桀，亟成譏犯。",
    "entities": [
      {
        "text": "弘毅",
        "label": "TITLE"
      },
      {
        "text": "汲黯",
        "label": "PER"
      },
      {
        "text": "崔琰",
        "label": "PER"
      }
    ]
  },
  {
    "sentence_id": "HCH_015_041_000153",
    "sentence": "張融標心託旨，全等塵外，吐納風雲，不論人物，而干君會友，敦義納忠，誕不越檢，常在名教。",
    "entities": [
      {
        "text": "張融",
        "label": "PER"
      },
      {
        "text": "風雲",
        "label": "LOC"
      },
      {
        "text": "教",
        "label": "PER"
      }
    ]
  },
  {
    "sentence_id": "HCH_015_041_000154",
    "sentence": "若夫奇偉之稱，則虞飜、陸績不得獨擅於前也。",
    "entities": []
  },
  {
    "sentence_id": "HCH_015_041_000155",
    "sentence": "贊曰：思光矯矯，萬里千仞。",
    "entities": [
      {
        "text": "思光",
        "label": "PER"
      },
      {
        "text": "萬里",
        "label": "NUM"
      },
      {
        "text": "千仞",
        "label": "NUM"
      }
    ]
  },
  {
    "sentence_id": "HCH_015_041_000156",
    "sentence": "升同應諧，黜同解擯。",
    "entities": []
  },
  {
    "sentence_id": "HCH_015_041_000157",
    "sentence": "務在連衡，不謀銷印。",
    "entities": []
  },
  {
    "sentence_id": "HCH_015_041_000158",
    "sentence": "彥倫辭辯，苦節清韻。",
    "entities": [
      {
        "text": "彥倫",
        "label": "PER"
      }
    ]
  },
  {
    "sentence_id": "HCH_015_041_000159",
    "sentence": "白馬橫擒，雲梯獨振。",
    "entities": [
      {
        "text": "白馬",
        "label": "LOC"
      },
      {
        "text": "雲梯",
        "label": "TITLE"
      }
    ]
  },
  {
    "sentence_id": "HCH_015_041_000160",
    "sentence": "張融《海賦》文多脫誤，諸本同。",
    "entities": [
      {
        "text": "張融",
        "label": "PER"
      },
      {
        "text": "海賦",
        "label": "TITLE"
      }
    ]
  },
  {
    "sentence_id": "HCH_015_041_000161",
    "sentence": "本南北朝作品在全世界都属于公有领域，因为作者逝世已经遠遠超过100年。",
    "entities": []
  }
]
